{
  "version": "0.1",
  "$schema": "https://raw.githubusercontent.com/streetsidesoftware/cspell/master/cspell.schema.json",
  "language": "en",
  "words": [
    "apikey",
    "bolditalic",
    "botcheck",
    "Dijk",
    "embeddable",
    "favourite",
    "focusring",
    "INFJ",
    "kahurangi",
    "lightitalic",
    "Māori",
    "Mediaworks",
    "mnyou",
    "necolas",
    "Ngāti",
    "noninteractive",
    "opensans",
    "posty",
    "Preact",
    "Rangi",
    "semibold",
    "semibolditalic",
    "stylelint",
    "Tipu",
    "truetype"
  ],
  "flagWords": [],
  "ignorePaths": [
    "package.json",
    "package-lock.json",
    "yarn.lock",
    "tsconfig.json",
    "node_modules/**",
    "public/**"
  ]
}
